feerepo/__init__.py
feerepo/repository/FeeRepository.py
feerepo/repository/__init__.py
feerepo/repository/account/AccountFeeRepository.py
feerepo/repository/account/__init__.py
feerepo/repository/exception/NoTradeFeeError.py
feerepo/repository/exception/__init__.py
feerepo/repository/instrument/InstrumentFeeRepository.py
feerepo/repository/instrument/__init__.py
persuader_technology_automata_fee_repository-0.1.1.dist-info/LICENSE
persuader_technology_automata_fee_repository-0.1.1.dist-info/METADATA
persuader_technology_automata_fee_repository-0.1.1.dist-info/WHEEL
persuader_technology_automata_fee_repository-0.1.1.dist-info/top_level.txt
persuader_technology_automata_fee_repository-0.1.1.dist-info/RECORD
